ratzetcalculator/__init__.py
ratzetcalculator/add.py
ratzetcalculator/divide.py
ratzetcalculator/multiply.py
ratzetcalculator/subtract.py
ratzetcalculator-0.0.1.dist-info/METADATA
ratzetcalculator-0.0.1.dist-info/WHEEL
ratzetcalculator-0.0.1.dist-info/top_level.txt
ratzetcalculator-0.0.1.dist-info/RECORD
