Metadata-Version: 2.1
Name: ratzetcalculator
Version: 0.0.1
Summary: calculator
Author: Abhishek raturi
Author-email: abhishek.raturi6@gmail.com
License: UNKNOWN
Keywords: python,first package
Platform: UNKNOWN
Classifier: Development Status :: 3 - Alpha
Classifier: Intended Audience :: Education
Classifier: Programming Language :: Python :: 2
Classifier: Programming Language :: Python :: 3
Classifier: Operating System :: MacOS :: MacOS X
Classifier: Operating System :: Microsoft :: Windows
